hserv/__init__.py
hserv/__version__.py
hserv/server.py
hserv/supabase/__init__.py
hserv/supabase/config.py
hserv/supabase/controller.py
hserv/webproxy/__init__.py
hserv/webproxy/nginx.py
hserv/webproxy/proxy.py
hserv-0.0.15.dist-info/LICENSE
hserv-0.0.15.dist-info/METADATA
hserv-0.0.15.dist-info/WHEEL
hserv-0.0.15.dist-info/top_level.txt
hserv-0.0.15.dist-info/RECORD
