Metadata-Version: 2.1
Name: hserv
Version: 0.0.15
Summary: cli / api toolchain for managing hydrocode servers
Author: Mirko Mälicke
Author-email: mirko@hydrocode.de
License-File: LICENSE
Requires-Dist: fabric
Requires-Dist: pyjwt
Requires-Dist: pyyaml
Requires-Dist: typing-extensions
Requires-Dist: requests
Requires-Dist: python-nginx
